LICENSE
MANIFEST.in
README.rst
setup.py
curl2requests/__init__.py
curl2requests/curl2requests.py
curl2requests.egg-info/PKG-INFO
curl2requests.egg-info/SOURCES.txt
curl2requests.egg-info/dependency_links.txt
curl2requests.egg-info/entry_points.txt
curl2requests.egg-info/top_level.txt