Metadata-Version: 1.1
Name: curl2requests
Version: 1.2
Summary: parse cURL command and return JSON data
Home-page: https://github.com/a4m/curl2requests
Author: mark0smith
Author-email: m11711237@gmail.com
License: GPL
Download-URL: https://github.com/a4m/curl2requests/archive/1.1.tar.gz
Keywords: cURL,requests
Platform: UNKNOWN
Classifier: Programming Language :: Python
Classifier: Development Status :: 3 - Alpha
